4-1 MUX/MUX.v
module mux (S1,S2,E,D0,D1,D2,D3,Y);
    input  S1,S2,E,D0,D1,D2,D3;
    output Y;
    
 assign  Y = (E & ~S1 & ~S2 & D0 | E & ~S1 & S2 & D1 | E & S1 & ~S2 & D2 | E & S1 & S2 & D3) ;   

endmodule

4-1 MUX/MUX_tb.v
`timescale 1ms / 1ms 
`include "MUX.v"
module MUX_tb; 
        reg S1,S2,E;
        reg D0=0,D1=0,D2=0,D3=0 ;
        wire Y;


    mux uut (S1,S2,E,D0,D1,D2,D3,Y);
    always begin
        D0= ~D0;
        D1= ~D0;
        D2= ~D2 & ~D1; 
        D3= ~D3 ^ D1 ; 
        #31.25;
    end

    initial begin
        //wavefrom 
        $dumpfile("MUX_tb.vcd");
        $dumpvars(0,MUX_tb);
        //Enable input 
        E=1;
        //select line veriation  
          
        S2=0;
        S1=0;

        #250;

        S2=1;
        S1=1;
        #250;

        S2=0;
        S1=1;
        #250;

        S2=1;
        S1=0;
        #250;

        $display("MUX simulated.");
        $finish;

    end

    

endmodule

4-1 MUX/MUX_tb.vcd
$date
	Mon Nov 16 10:21:33 2020
$end
$version
	Icarus Verilog
$end
$timescale
	1ms
$end
$scope module MUX_tb $end
$var wire 1 ! Y $end
$var reg 1 " D0 $end
$var reg 1 # D1 $end
$var reg 1 $ D2 $end
$var reg 1 % D3 $end
$var reg 1 & E $end
$var reg 1 ' S1 $end
$var reg 1 ( S2 $end
$scope module uut $end
$var wire 1 " D0 $end
$var wire 1 # D1 $end
$var wire 1 $ D2 $end
$var wire 1 % D3 $end
$var wire 1 & E $end
$var wire 1 ' S1 $end
$var wire 1 ( S2 $end
$var wire 1 ! Y $end
$upscope $end
$upscope $end
$enddefinitions $end
#0
$dumpvars
0(
0'
1&
1%
1$
0#
1"
1!
$end
#31
0!
0$
1#
0"
#62
1!
0%
1$
0#
1"
#93
0!
0$
1#
0"
#124
1!
1%
1$
0#
1"
#155
0!
0$
1#
0"
#186
1!
0%
1$
0#
1"
#217
0!
0$
1#
0"
#248
1!
1%
1$
0#
1"
#250
1'
1(
#279
0$
1#
0"
#310
0!
0%
1$
0#
1"
#341
0$
1#
0"
#372
1!
1%
1$
0#
1"
#403
0$
1#
0"
#434
0!
0%
1$
0#
1"
#465
0$
1#
0"
#496
1!
1%
1$
0#
1"
#500
1!
0(
#527
0!
0$
1#
0"
#558
1!
0%
1$
0#
1"
#589
0!
0$
1#
0"
#620
1!
1%
1$
0#
1"
#651
0!
0$
1#
0"
#682
1!
0%
1$
0#
1"
#713
0!
0$
1#
0"
#744
1!
1%
1$
0#
1"
#750
0!
0'
1(
#775
1!
0$
1#
0"
#806
0!
0%
1$
0#
1"
#837
1!
0$
1#
0"
#868
0!
1%
1$
0#
1"
#899
1!
0$
1#
0"
#930
0!
0%
1$
0#
1"
#961
1!
0$
1#
0"
#992
0!
1%
1$
0#
1"
